semvercomp/Version.py
semvercomp/__init__.py
semvercomp/utils.py
semvercomp/validators.py
tests/__init__.py
tests/test_Version.py
tests/test_utils.py
tests/test_validators.py
semvercomp-0.1.1.dist-info/LICENSE
semvercomp-0.1.1.dist-info/METADATA
semvercomp-0.1.1.dist-info/WHEEL
semvercomp-0.1.1.dist-info/top_level.txt
semvercomp-0.1.1.dist-info/RECORD
