Metadata-Version: 2.1
Name: semvercomp
Version: 0.1.1
Summary: Semantic Version Comparison for Python
Home-page: https://github.com/estebanborai/semvercomp
Author: Esteban Borai
Author-email: estebanborai@outlook.com
License: UNKNOWN
Platform: UNKNOWN
Classifier: Programming Language :: Python :: 3
Classifier: License :: OSI Approved :: MIT License
Classifier: Operating System :: OS Independent
